{
"type": "FeatureCollection",
"name": "sites",
"crs": { "type": "name", "properties": { "name": "urn:ogc:def:crs:OGC:1.3:CRS84" } },
"features": [
{ "type": "Feature", "properties": { "ID": "1348771_1" }, "geometry": { "type": "Point", "coordinates": [ -48.746351981568502, -3.01269121745167 ] } },
{ "type": "Feature", "properties": { "ID": "1348771_2" }, "geometry": { "type": "Point", "coordinates": [ -48.742769731880699, -3.04902469160896 ] } },
{ "type": "Feature", "properties": { "ID": "1348771_3" }, "geometry": { "type": "Point", "coordinates": [ -48.7405044182984, -2.9701005317819 ] } },
{ "type": "Feature", "properties": { "ID": "1348771_4" }, "geometry": { "type": "Point", "coordinates": [ -48.740861491310802, -3.05851268568669 ] } },
{ "type": "Feature", "properties": { "ID": "1348771_5" }, "geometry": { "type": "Point", "coordinates": [ -48.7306844355046, -3.02296407824119 ] } },
{ "type": "Feature", "properties": { "ID": "1348771_6" }, "geometry": { "type": "Point", "coordinates": [ -48.7194371917045, -2.98307447507015 ] } },
{ "type": "Feature", "properties": { "ID": "1348771_7" }, "geometry": { "type": "Point", "coordinates": [ -48.748507298148198, -3.01405170754731 ] } },
{ "type": "Feature", "properties": { "ID": "1348771_8" }, "geometry": { "type": "Point", "coordinates": [ -48.730499787809201, -2.98174147513121 ] } },
{ "type": "Feature", "properties": { "ID": "1348771_9" }, "geometry": { "type": "Point", "coordinates": [ -48.740503866784898, -2.97037173144116 ] } },
{ "type": "Feature", "properties": { "ID": "1348771_10" }, "geometry": { "type": "Point", "coordinates": [ -48.760299349896002, -3.05177353685137 ] } },
{ "type": "Feature", "properties": { "ID": "1348771_11" }, "geometry": { "type": "Point", "coordinates": [ -48.756857200892, -3.02030671291386 ] } },
{ "type": "Feature", "properties": { "ID": "1348771_12" }, "geometry": { "type": "Point", "coordinates": [ -48.763624653496301, -3.0089301272638 ] } },
{ "type": "Feature", "properties": { "ID": "1348771_13" }, "geometry": { "type": "Point", "coordinates": [ -48.7063384306486, -3.05491355418096 ] } },
{ "type": "Feature", "properties": { "ID": "1348771_14" }, "geometry": { "type": "Point", "coordinates": [ -48.727801153747002, -2.98227827539249 ] } },
{ "type": "Feature", "properties": { "ID": "1348771_15" }, "geometry": { "type": "Point", "coordinates": [ -48.749781543629801, -3.05012425624576 ] } },
{ "type": "Feature", "properties": { "ID": "1348771_16" }, "geometry": { "type": "Point", "coordinates": [ -48.754530460102202, -2.97067167840624 ] } },
{ "type": "Feature", "properties": { "ID": "1348771_17" }, "geometry": { "type": "Point", "coordinates": [ -48.730711998755801, -3.00967539665413 ] } },
{ "type": "Feature", "properties": { "ID": "1348771_18" }, "geometry": { "type": "Point", "coordinates": [ -48.734676051831002, -3.0492788013329 ] } },
{ "type": "Feature", "properties": { "ID": "1348771_19" }, "geometry": { "type": "Point", "coordinates": [ -48.748808763984101, -2.9985938090947 ] } },
{ "type": "Feature", "properties": { "ID": "1348771_20" }, "geometry": { "type": "Point", "coordinates": [ -48.756150081036999, -2.97013257872738 ] } }
]
}
